pymaya/__init__.py
pymaya/exceptions.py
pymaya/maya.py
pymaya/maya_base.py
pymaya/maya_funds.py
pymaya/maya_security.py
pymaya/utils.py
pymaya/request_classes/__init__.py
pymaya/request_classes/maya_all_securities_request.py
pymaya/request_classes/maya_base_request.py
pymaya/request_classes/maya_fund_base_request.py
pymaya/request_classes/maya_fund_details_request.py
pymaya/request_classes/maya_historical_request.py
pymaya/request_classes/maya_security_base_request.py
pymaya/request_classes/maya_security_data_request.py
pymaya/request_classes/maya_security_details_request.py
pymaya/request_classes/maya_security_request.py
pymaya-0.5.1.dist-info/licenses/LICENSE
pymaya-0.5.1.dist-info/METADATA
pymaya-0.5.1.dist-info/WHEEL
pymaya-0.5.1.dist-info/top_level.txt
pymaya-0.5.1.dist-info/RECORD
